[
   {
      "timestamp": "2019-06-06T00:17:34.848Z",
      "userFullName": "David Budimir",
      "dough": "Traditional",
      "sauce": "Classic Tomato",
      "cheese": "Mozarella",
      "veggies": "Broccoli, Grilled Onion",
      "protiens": "Chicken, Scrambled Egg",
      "finishes": "Pickled Red Onion, Caesar Dressing",
      "orderName": "Wednesday Pizza Day",
      "description": "Just testing things out."
   },
   {
      "timestamp": "2019-06-06T00:18:24.013Z",
      "userFullName": "Bruce Wayne",
      "dough": "Gluten-Free",
      "sauce": "Basil Pesto",
      "cheese": "Vegan Mozzarella",
      "veggies": "Jalapeno, Pineapple",
      "protiens": "Scrambled Egg",
      "finishes": "Arugula, Crumbled Croutons",
      "orderName": "The Healthy Melty",
      "description": "A vegan pie?"
   }
]
